MANIFEST.in
README.rst
setup.py
comicgen/__init__.py
comicgen.egg-info/PKG-INFO
comicgen.egg-info/SOURCES.txt
comicgen.egg-info/dependency_links.txt
comicgen.egg-info/entry_points.txt
comicgen.egg-info/requires.txt
comicgen.egg-info/top_level.txt
comicgen/templates/ncx.jinja2
comicgen/templates/opf.jinja2
comicgen/templates/page.jinja2