Metadata-Version: 1.1
Name: comicgen
Version: 0.3
Summary: A command-line tool to make ebook of comics.
Home-page: https://github.com/wutali/comicgen
Author: Takahiro Fujiwara
Author-email: email@wuta.li
License: UNKNOWN
Download-URL: https://github.com/wutali/comicgen/tarball/master
Platform: UNKNOWN
